README.md
setup.cfg
setup.py
qreport/__init__.py
qreport/db.py
qreport/report.py
qreport.egg-info/PKG-INFO
qreport.egg-info/SOURCES.txt
qreport.egg-info/dependency_links.txt
qreport.egg-info/not-zip-safe
qreport.egg-info/requires.txt
qreport.egg-info/top_level.txt
qreport/templates/_filter.html
qreport/templates/_forms.html
qreport/templates/_script.js
qreport/templates/_table.html
qreport/templates/_title.html
qreport/templates/index.html