Metadata-Version: 1.0
Name: qreport
Version: 0.6
Summary: Simple Report
Home-page: https://github.com/rvettori/qreport
Author: Rafael Vettori
Author-email: rafael.vettori@gmail.com
License: MIT
Platform: UNKNOWN
